{"minified":"composer/2.0","packages":{"typo3/cms-cli":[{"name":"typo3/cms-cli","description":"TYPO3 command line binary","keywords":[],"homepage":"https://typo3.org","version":"3.1.1","version_normalized":"3.1.1.0","license":["GPL-2.0-or-later"],"authors":[],"source":{"url":"https://github.com/TYPO3/cms-cli.git","type":"git","reference":"d8947732ff5a6dc52829e88cb1c761124475c0e8"},"dist":{"url":"https://api.github.com/repos/TYPO3/cms-cli/zipball/d8947732ff5a6dc52829e88cb1c761124475c0e8","type":"zip","shasum":"","reference":"d8947732ff5a6dc52829e88cb1c761124475c0e8"},"type":"library","support":{"issues":"https://github.com/TYPO3/cms-cli/issues","source":"https://github.com/TYPO3/cms-cli/tree/3.1.1"},"funding":[],"time":"2023-08-15T10:14:53+00:00","bin":["typo3"],"require":{"php":"^7.0 || ^8.0"}},{"version":"3.1.0","version_normalized":"3.1.0.0","source":{"url":"https://github.com/TYPO3/cms-cli.git","type":"git","reference":"1572143c88ec08d238e417de55c9813fb949e783"},"dist":{"url":"https://api.github.com/repos/TYPO3/cms-cli/zipball/1572143c88ec08d238e417de55c9813fb949e783","type":"zip","shasum":"","reference":"1572143c88ec08d238e417de55c9813fb949e783"},"support":{"issues":"https://github.com/TYPO3/cms-cli/issues","source":"https://github.com/TYPO3/cms-cli/tree/3.1.0"},"time":"2021-03-01T12:18:57+00:00"},{"version":"3.0.0","version_normalized":"3.0.0.0","source":{"url":"https://github.com/TYPO3/cms-cli.git","type":"git","reference":"bfb13f4ab6a505104662b79c18108f41c48e9288"},"dist":{"url":"https://api.github.com/repos/TYPO3/cms-cli/zipball/bfb13f4ab6a505104662b79c18108f41c48e9288","type":"zip","shasum":"","reference":"bfb13f4ab6a505104662b79c18108f41c48e9288"},"support":{"issues":"https://github.com/TYPO3/cms-cli/issues","source":"https://github.com/TYPO3/cms-cli/tree/3.0.0"},"time":"2021-02-09T12:45:27+00:00","require":{"php":"^7.0"}},{"version":"2.0.0","version_normalized":"2.0.0.0","source":{"url":"https://github.com/TYPO3/cms-cli.git","type":"git","reference":"215a0bf5c446b4e0b20f4562bbaf3d6215a5ee82"},"dist":{"url":"https://api.github.com/repos/TYPO3/cms-cli/zipball/215a0bf5c446b4e0b20f4562bbaf3d6215a5ee82","type":"zip","shasum":"","reference":"215a0bf5c446b4e0b20f4562bbaf3d6215a5ee82"},"support":{"issues":"https://github.com/TYPO3/cms-cli/issues","source":"https://github.com/TYPO3/cms-cli/tree/master"},"time":"2018-03-08T20:16:43+00:00","funding":"__unset"},{"version":"1.0.2","version_normalized":"1.0.2.0","license":["GPL-2.0+"],"source":{"url":"https://github.com/TYPO3/cms-cli.git","type":"git","reference":"c27c3580b384353414d0b4ff61137127798f8189"},"dist":{"url":"https://api.github.com/repos/TYPO3/cms-cli/zipball/c27c3580b384353414d0b4ff61137127798f8189","type":"zip","shasum":"","reference":"c27c3580b384353414d0b4ff61137127798f8189"},"time":"2017-09-06T12:09:47+00:00","autoload":{"psr-4":{"TYPO3\\CMS\\Cli\\":"src"}}},{"version":"1.0.1","version_normalized":"1.0.1.0","source":{"url":"https://github.com/TYPO3/cms-cli.git","type":"git","reference":"713666d40ee56c1a362d1ce7c3f929613fc033b9"},"dist":{"url":"https://api.github.com/repos/TYPO3/cms-cli/zipball/713666d40ee56c1a362d1ce7c3f929613fc033b9","type":"zip","shasum":"","reference":"713666d40ee56c1a362d1ce7c3f929613fc033b9"},"time":"2017-07-28T09:15:35+00:00","require":{"php":"^7.0","typo3/cms-core":"^8.7 || ^9.0@dev"}},{"version":"1.0.0","version_normalized":"1.0.0.0","source":{"url":"https://github.com/TYPO3/cms-cli.git","type":"git","reference":"b728de7e8b993745ff78bdd38634ed0c44706a28"},"dist":{"url":"https://api.github.com/repos/TYPO3/cms-cli/zipball/b728de7e8b993745ff78bdd38634ed0c44706a28","type":"zip","shasum":"","reference":"b728de7e8b993745ff78bdd38634ed0c44706a28"},"time":"2017-07-25T17:43:19+00:00","require":{"php":"^7.0","typo3/cms-core":"^8.7 || ^9.0"}}]},"security-advisories":[],"last-modified":"Thu, 18 Apr 2024 12:42:30 GMT"}